bael.project-0.2.7-py3.6-nspkg.pth
bael/project/__init__.py
bael/project/base.py
bael/project/cmd.py
bael/project/core.py
bael/project/datafile.py
bael/project/develop.py
bael/project/folders.py
bael/project/git.py
bael/project/project.py
bael/project/recipe.py
bael/project/tasks.py
bael/project/virtualenv.py
bael/project/templates/gitignore.tpl
bael/project/templates/setup.py
bael/project/templates/setuppy.jinja2
bael.project-0.2.7.dist-info/DESCRIPTION.rst
bael.project-0.2.7.dist-info/METADATA
bael.project-0.2.7.dist-info/RECORD
bael.project-0.2.7.dist-info/WHEEL
bael.project-0.2.7.dist-info/entry_points.txt
bael.project-0.2.7.dist-info/metadata.json
bael.project-0.2.7.dist-info/namespace_packages.txt
bael.project-0.2.7.dist-info/top_level.txt
