Metadata-Version: 2.0
Name: bael.project
Version: 0.2.7
Summary: Simple project generator.
Home-page: UNKNOWN
Author: UNKNOWN
Author-email: UNKNOWN
License: Apache License 2.0
Platform: UNKNOWN
Requires-Dist: baelfire (>=0.4.1)
Requires-Dist: virtualenv
